textgrab/__init__.py
textgrab/crop_mask_item.py
textgrab/mainwindow.py
textgrab/mainwindow.ui
textgrab/run.py
textgrab/ui_mainwindow.py
textgrab-1.0.0.dist-info/entry_points.txt
textgrab-1.0.0.dist-info/LICENSE
textgrab-1.0.0.dist-info/WHEEL
textgrab-1.0.0.dist-info/METADATA
textgrab-1.0.0.dist-info/RECORD
