Metadata-Version: 2.1
Name: textgrab
Version: 1.0.0
Summary: 
License: GPLv2
Author: PowerSnail
Author-email: hj@powersnail.com
Requires-Python: >=3.9,<3.10
Classifier: License :: Other/Proprietary License
Classifier: Programming Language :: Python :: 3
Classifier: Programming Language :: Python :: 3.9
Requires-Dist: Pillow (>=8.2.0,<9.0.0)
Requires-Dist: PySide6
Requires-Dist: appdirs (>=1.4.4,<2.0.0)
Requires-Dist: docopt-ng (>=0.7.2,<0.8.0)
Requires-Dist: pytesseract (>=0.3.7,<0.4.0)
